circman/__init__.py
circman/__main__.py
circman/py.typed
circman-0.3.0.dist-info/LICENSE
circman-0.3.0.dist-info/METADATA
circman-0.3.0.dist-info/WHEEL
circman-0.3.0.dist-info/entry_points.txt
circman-0.3.0.dist-info/RECORD
