Metadata-Version: 2.1
Name: circman
Version: 0.3.0
Summary: CircuitPython Manager
Home-page: https://github.com/rbedia/circman
License: MIT
Author: Rafael Bedia
Author-email: rafael.bedia@gmail.com
Requires-Python: >=3.8,<4.0
Classifier: Development Status :: 4 - Beta
Classifier: License :: OSI Approved :: MIT License
Classifier: Programming Language :: Python :: 3
Classifier: Programming Language :: Python :: 3.8
Classifier: Programming Language :: Python :: 3.9
Classifier: Programming Language :: Python :: 3.10
Classifier: Programming Language :: Python :: 3.11
Requires-Dist: click (>=8.0.1)
Requires-Dist: platformdirs (>=3.0.0,<4.0.0)
Requires-Dist: setuptools (>=67.4.0,<68.0.0)
Project-URL: Changelog, https://github.com/rbedia/circman/releases
Project-URL: Documentation, https://circman.readthedocs.io
Project-URL: Repository, https://github.com/rbedia/circman
